wagtailstartproject/__init__.py
wagtailstartproject/wagtailstartproject.py
wagtailstartproject/legacy_project_template/.editorconfig
wagtailstartproject/legacy_project_template/Makefile
wagtailstartproject/legacy_project_template/bitbucket-pipelines.yml
wagtailstartproject/legacy_project_template/manage.py
wagtailstartproject/legacy_project_template/requirements-dev.txt
wagtailstartproject/legacy_project_template/requirements.txt
wagtailstartproject/legacy_project_template/pages/__init__.py
wagtailstartproject/legacy_project_template/pages/models.py
wagtailstartproject/legacy_project_template/pages/migrations/0001_initial.py
wagtailstartproject/legacy_project_template/pages/migrations/0002_create_homepage.py
wagtailstartproject/legacy_project_template/pages/migrations/__init__.py
wagtailstartproject/legacy_project_template/pages/templates/pages/content_page.html
wagtailstartproject/legacy_project_template/pages/templates/pages/home_page.html
wagtailstartproject/legacy_project_template/project_name/__init__.py
wagtailstartproject/legacy_project_template/project_name/settings_default.py
wagtailstartproject/legacy_project_template/project_name/site_settings_example.py
wagtailstartproject/legacy_project_template/project_name/urls.py
wagtailstartproject/legacy_project_template/project_name/wsgi.py
wagtailstartproject/legacy_project_template/project_name/static/css/project_name.css
wagtailstartproject/legacy_project_template/project_name/static/js/project_name.js
wagtailstartproject/legacy_project_template/project_name/templates/404.html
wagtailstartproject/legacy_project_template/project_name/templates/500.html
wagtailstartproject/legacy_project_template/project_name/templates/base.html
wagtailstartproject/legacy_project_template/search/__init__.py
wagtailstartproject/legacy_project_template/search/views.py
wagtailstartproject/legacy_project_template/search/templates/search/search.html
wagtailstartproject/project_template/.bumpversion.cfg
wagtailstartproject-0.1.5.dist-info/DESCRIPTION.rst
wagtailstartproject-0.1.5.dist-info/METADATA
wagtailstartproject-0.1.5.dist-info/RECORD
wagtailstartproject-0.1.5.dist-info/WHEEL
wagtailstartproject-0.1.5.dist-info/entry_points.txt
wagtailstartproject-0.1.5.dist-info/metadata.json
wagtailstartproject-0.1.5.dist-info/pbr.json
wagtailstartproject-0.1.5.dist-info/top_level.txt
