Metadata-Version: 2.0
Name: wagtailstartproject
Version: 0.1.5
Summary: This app contains a custom project template and a custom wagtail start command to allow creating customized wagtail setups
Home-page: https://github.com/leukeleu/wagtail-startproject
Author: Leukeleu
Author-email: info@leukeleu.nl
License: MIT
Keywords: wagtail,startproject
Platform: UNKNOWN
Classifier: Intended Audience :: Developers
Classifier: License :: OSI Approved :: MIT License
Classifier: Operating System :: OS Independent
Classifier: Programming Language :: Python
Requires-Dist: django
